aruna/api/dataproxy/services/v2/bundler_service_pb2.py
aruna/api/dataproxy/services/v2/bundler_service_pb2.pyi
aruna/api/dataproxy/services/v2/bundler_service_pb2_grpc.py
aruna/api/dataproxy/services/v2/dataproxy_service_pb2.py
aruna/api/dataproxy/services/v2/dataproxy_service_pb2.pyi
aruna/api/dataproxy/services/v2/dataproxy_service_pb2_grpc.py
aruna/api/hooks/services/v2/hooks_service_pb2.py
aruna/api/hooks/services/v2/hooks_service_pb2.pyi
aruna/api/hooks/services/v2/hooks_service_pb2_grpc.py
aruna/api/notification/services/v2/notification_service_pb2.py
aruna/api/notification/services/v2/notification_service_pb2.pyi
aruna/api/notification/services/v2/notification_service_pb2_grpc.py
aruna/api/storage/models/v2/models_pb2.py
aruna/api/storage/models/v2/models_pb2.pyi
aruna/api/storage/models/v2/models_pb2_grpc.py
aruna/api/storage/services/v2/authorization_service_pb2.py
aruna/api/storage/services/v2/authorization_service_pb2.pyi
aruna/api/storage/services/v2/authorization_service_pb2_grpc.py
aruna/api/storage/services/v2/collection_service_pb2.py
aruna/api/storage/services/v2/collection_service_pb2.pyi
aruna/api/storage/services/v2/collection_service_pb2_grpc.py
aruna/api/storage/services/v2/data_replication_service_pb2.py
aruna/api/storage/services/v2/data_replication_service_pb2.pyi
aruna/api/storage/services/v2/data_replication_service_pb2_grpc.py
aruna/api/storage/services/v2/dataset_service_pb2.py
aruna/api/storage/services/v2/dataset_service_pb2.pyi
aruna/api/storage/services/v2/dataset_service_pb2_grpc.py
aruna/api/storage/services/v2/endpoint_service_pb2.py
aruna/api/storage/services/v2/endpoint_service_pb2.pyi
aruna/api/storage/services/v2/endpoint_service_pb2_grpc.py
aruna/api/storage/services/v2/info_service_pb2.py
aruna/api/storage/services/v2/info_service_pb2.pyi
aruna/api/storage/services/v2/info_service_pb2_grpc.py
aruna/api/storage/services/v2/license_service_pb2.py
aruna/api/storage/services/v2/license_service_pb2.pyi
Aruna_Python_API-2.0.2.dist-info/METADATA
Aruna_Python_API-2.0.2.dist-info/WHEEL
Aruna_Python_API-2.0.2.dist-info/top_level.txt
Aruna_Python_API-2.0.2.dist-info/RECORD
