Metadata-Version: 2.1
Name: Aruna-Python-API
Version: 2.0.2
Summary: Aruna Object Storage Python API builds
Home-page: https://github.com/ArunaStorage/python-api
Author: Sebastian Beyvers, Jannis Hochmuth, Lukas Brehm
Author-email: sebastian.beyvers@computational.bio.uni-giessen.de, jannis.hochmuth@computational.bio.uni-giessen.de, lukas.brehm@computational.bio.uni-giessen.de
License: Apache 2.0
Requires-Dist: protobuf
Requires-Dist: grpcio
Requires-Dist: google-api-python-client
